onelogin_aws_login/__init__.py
onelogin_aws_login/__main__.py
onelogin_aws_login/argparse.py
onelogin_aws_login/cli.py
onelogin_aws_login/configuration.py
onelogin_aws_login/credentials.py
onelogin_aws_login/userquery.py
onelogin_aws_login-1.4.dist-info/METADATA
onelogin_aws_login-1.4.dist-info/WHEEL
onelogin_aws_login-1.4.dist-info/entry_points.txt
onelogin_aws_login-1.4.dist-info/top_level.txt
onelogin_aws_login-1.4.dist-info/RECORD
