Metadata-Version: 2.1
Name: onelogin-aws-login
Version: 1.4
Home-page: 
Author: 
Author-email: 
Requires-Python: >=3.8
Requires-Dist: boto3
Requires-Dist: onelogin (==2.0.4)
Requires-Dist: keyring
Requires-Dist: requests
